rocketmq_client/__init__.py
rocketmq_client/apache/rocketmq/v2/__init__.py
rocketmq_client/apache/rocketmq/v2/admin_pb2.py
rocketmq_client/apache/rocketmq/v2/admin_pb2.pyi
rocketmq_client/apache/rocketmq/v2/admin_pb2_grpc.py
rocketmq_client/apache/rocketmq/v2/definition_pb2.py
rocketmq_client/apache/rocketmq/v2/definition_pb2.pyi
rocketmq_client/apache/rocketmq/v2/definition_pb2_grpc.py
rocketmq_client/apache/rocketmq/v2/service_pb2.py
rocketmq_client/apache/rocketmq/v2/service_pb2.pyi
rocketmq_client/apache/rocketmq/v2/service_pb2_grpc.py
rocketmq_client/foo.py
rocketmq_client-0.1.0.dist-info/METADATA
rocketmq_client-0.1.0.dist-info/WHEEL
rocketmq_client-0.1.0.dist-info/RECORD
