Metadata-Version: 2.1
Name: rocketmq-client
Version: 0.1.0
Summary: RocketMQ Python Client
Author: Aaron Ai
Author-email: yangkun.ayk@gmail.com
Requires-Python: >=3.7,<4.0
Classifier: Programming Language :: Python :: 3
Classifier: Programming Language :: Python :: 3.7
Classifier: Programming Language :: Python :: 3.8
Classifier: Programming Language :: Python :: 3.9
Classifier: Programming Language :: Python :: 3.10
Classifier: Programming Language :: Python :: 3.11
Requires-Dist: grpcio (>=1.50.0,<2.0.0)
Requires-Dist: grpcio-tools (>=1.50.0,<2.0.0)
